certification/__init__.py
certification/admin.py
certification/apps.py
certification/conf.py
certification/manager.py
certification/signals_define.py
certification/tests.py
certification/accredible/__init__.py
certification/accredible/credentials.py
certification/accredible/groups.py
certification/management/__init__.py
certification/management/commands/__init__.py
certification/migrations/0001_initial.py
certification/migrations/0002_auto_20181017_1424.py
certification/migrations/0003_auto_20181024_0932.py
certification/migrations/0004_auto_20190524_1020.py
certification/migrations/0005_auto_20190627_1404.py
certification/migrations/0006_certificationgroup_instructor_name.py
certification/migrations/__init__.py
certification/models/__init__.py
certification/models/certification_credential.py
certification/models/certification_group.py
certification/signals/__init__.py
certification/signals/create_certification.py
certification/tasks/__init__.py
certification/tasks/create_accredible_consultant_role_group.py
certification/tasks/create_accredible_group.py
certification/tasks/create_accredible_group_credential.py
certification/tasks/create_accredible_simple_credential.py
certification/tasks/delete_accredible_group.py
certification/tasks/update_accredible_group.py
django_accredible-0.5.5.dist-info/AUTHORS.rst
django_accredible-0.5.5.dist-info/LICENSE
django_accredible-0.5.5.dist-info/METADATA
django_accredible-0.5.5.dist-info/WHEEL
django_accredible-0.5.5.dist-info/top_level.txt
django_accredible-0.5.5.dist-info/RECORD
