Metadata-Version: 2.1
Name: django-accredible
Version: 0.5.5
Summary: Integrate Accredible certification in a Django App
Home-page: https://github.com/tomasgarzon/django-accredible
Author: Tomas Garzon
Author-email: tomasgarzonhervas@gmail.com
License: MIT
Keywords: django-accredible
Platform: UNKNOWN
Classifier: Development Status :: 3 - Alpha
Classifier: Framework :: Django :: 2.0
Classifier: Intended Audience :: Developers
Classifier: License :: OSI Approved :: BSD License
Classifier: Natural Language :: English
Classifier: Programming Language :: Python :: 2
Classifier: Programming Language :: Python :: 2.7
Classifier: Programming Language :: Python :: 3
Classifier: Programming Language :: Python :: 3.4
Classifier: Programming Language :: Python :: 3.5
Classifier: Programming Language :: Python :: 3.6
Requires-Dist: django-model-utils (>=2.0)
